molcompview/__init__.py
molcompview/actions.py
molcompview/components.py
molcompview/functions.py
molcompview/main.py
molcompview/data/endocrine-receptor/endocrine.csv
molcompview-0.1.7.dist-info/licenses/LICENSE
molcompview-0.1.7.dist-info/METADATA
molcompview-0.1.7.dist-info/WHEEL
molcompview-0.1.7.dist-info/entry_points.txt
molcompview-0.1.7.dist-info/top_level.txt
molcompview-0.1.7.dist-info/RECORD
