Metadata-Version: 2.4
Name: molcompview
Version: 0.1.7
Summary: MolCompass Visualization Tool: Visualize your Chemical Space
Home-page: https://github.com/sergsb/molcompview
Author: Sergey Sosnin
Author-email: sergey.sosnin@univie.ac.at
License: MIT
Keywords: chemistry,cheminformatics,t-SNE,visualization,chemical space
Classifier: Programming Language :: Python :: 3
Classifier: Programming Language :: Python :: 3.6
Classifier: License :: OSI Approved :: MIT License
Classifier: Operating System :: OS Independent
Classifier: Development Status :: 3 - Alpha
Classifier: Topic :: Scientific/Engineering :: Chemistry
Classifier: Intended Audience :: Science/Research
Requires-Python: >=3.6
License-File: LICENSE
Requires-Dist: molcomplib
Requires-Dist: rdkit
Requires-Dist: appdata
Requires-Dist: numpy
Requires-Dist: pandas
Requires-Dist: scipy
Requires-Dist: scikit-learn
Requires-Dist: fire
Requires-Dist: dash
Requires-Dist: dash-bootstrap-components
Dynamic: author
Dynamic: author-email
Dynamic: classifier
Dynamic: description
Dynamic: description-content-type
Dynamic: home-page
Dynamic: keywords
Dynamic: license
Dynamic: license-file
Dynamic: requires-dist
Dynamic: requires-python
Dynamic: summary
